azure_vault_loader/__init__.py
azure_vault_loader/_version.py
azure_vault_loader/cli.py
azure_vault_loader/crypto_utils.py
azure_vault_loader-0.1.0.dist-info/LICENSE
azure_vault_loader-0.1.0.dist-info/METADATA
azure_vault_loader-0.1.0.dist-info/WHEEL
azure_vault_loader-0.1.0.dist-info/entry_points.txt
azure_vault_loader-0.1.0.dist-info/top_level.txt
azure_vault_loader-0.1.0.dist-info/RECORD
