Metadata-Version: 2.1
Name: azure-vault-loader
Version: 0.1.0
Summary: Load secrets from Azure key vault into the environment of a process
Home-page: https://github.com/jason-weirather/azure-vault-loader
Author: Jason L Weirather
Author-email: jason.weirather@gmail.com
License: UNKNOWN
Platform: UNKNOWN
Classifier: Development Status :: 3 - Alpha
Classifier: Intended Audience :: Developers
Classifier: License :: OSI Approved :: Apache Software License
Classifier: Programming Language :: Python :: 3.9
Requires-Dist: azure-keyvault-secrets
Requires-Dist: azure-identity
